odoo/addons/event_session/README.rst
odoo/addons/event_session/__init__.py
odoo/addons/event_session/__manifest__.py
odoo/addons/event_session/i18n/es.po
odoo/addons/event_session/i18n/event_session.pot
odoo/addons/event_session/i18n/nl.po
odoo/addons/event_session/models/__init__.py
odoo/addons/event_session/models/event.py
odoo/addons/event_session/models/event_mail.py
odoo/addons/event_session/models/event_session.py
odoo/addons/event_session/models/res_config_settings.py
odoo/addons/event_session/security/event_session_security.xml
odoo/addons/event_session/security/ir.model.access.csv
odoo/addons/event_session/static/description/icon.png
odoo/addons/event_session/tests/__init__.py
odoo/addons/event_session/tests/test_session.py
odoo/addons/event_session/views/event_session_view.xml
odoo/addons/event_session/views/event_view.xml
odoo/addons/event_session/wizards/__init__.py
odoo/addons/event_session/wizards/wizard_event_session.py
odoo/addons/event_session/wizards/wizard_event_session_view.xml
odoo11_addon_event_session-11.0.1.0.1.dist-info/METADATA
odoo11_addon_event_session-11.0.1.0.1.dist-info/WHEEL
odoo11_addon_event_session-11.0.1.0.1.dist-info/top_level.txt
odoo11_addon_event_session-11.0.1.0.1.dist-info/RECORD
